audentes/__init__.py
audentes/core.py
audentes/helpers.py
tests/__init__.py
tests/audentes_tests.py
tests/context.py
audentes-0.1.9.dist-info/METADATA
audentes-0.1.9.dist-info/WHEEL
audentes-0.1.9.dist-info/top_level.txt
audentes-0.1.9.dist-info/RECORD
