Metadata-Version: 2.1
Name: audentes
Version: 0.1.9
Summary: A package for writing component tests with docker compose
Home-page: https://gitlab.com/magnus.odman/audentes
Author: Magnus Odman
Author-email: magnus.odman@gmail.com
License: UNKNOWN
Platform: UNKNOWN
Classifier: Programming Language :: Python :: 3
Classifier: License :: OSI Approved :: MIT License
Classifier: Operating System :: OS Independent
Requires-Dist: requests
Requires-Dist: ruamel.yaml
